{"cameraMode":{"drawMode":0,"name":"Shaded","section":"Shading Mode"},"sceneLighting":true,"audioPlay":false,"sceneViewState":{"m_AlwaysRefresh":false,"showFog":true,"showSkybox":true,"showFlares":true,"showImageEffects":true,"showParticleSystems":true,"showVisualEffectGraphs":true,"m_FxEnabled":true},"in2DMode":false,"pivot":{"x":0.12823486328125,"y":11.166452407836914,"z":-9.597043991088868},"rotation":{"x":-0.13228470087051392,"y":0.8598650693893433,"z":-0.28048133850097659,"w":-0.4055422246456146},"size":16.819881439208986,"orthographic":false}